gcr_cli/__init__.py
gcr_cli/gcr.py
gcr_cli-0.1.0.dist-info/entry_points.txt
gcr_cli-0.1.0.dist-info/WHEEL
gcr_cli-0.1.0.dist-info/METADATA
gcr_cli-0.1.0.dist-info/RECORD
